ai_text_to_sql/__init__.py
ai_text_to_sql/config/logging.yaml
ai_text_to_sql/config_parser.py
ai_text_to_sql/data_connectors/__init__.py
ai_text_to_sql/data_connectors/data_connector.py
ai_text_to_sql/data_connectors/mariadb_connector.py
ai_text_to_sql/data_connectors/mssql_connector.py
ai_text_to_sql/data_connectors/mysql_connector.py
ai_text_to_sql/data_connectors/postgresql_connector.py
ai_text_to_sql/data_connectors/sqlite_connector.py
ai_text_to_sql/exceptions.py
ai_text_to_sql/llm_connectors/__init__.py
ai_text_to_sql/llm_connectors/llm_connector.py
ai_text_to_sql/llm_connectors/openai_connector.py
ai_text_to_sql/text_to_sql.py
ai_text_to_sql/text_to_sql_agent.py
ai_text_to_sql/text_to_sql_chat.py
ai_text_to_sql-0.3.0.dist-info/LICENSE
ai_text_to_sql-0.3.0.dist-info/METADATA
ai_text_to_sql-0.3.0.dist-info/WHEEL
ai_text_to_sql-0.3.0.dist-info/RECORD
