Metadata-Version: 2.1
Name: ai-text-to-sql
Version: 0.3.0
Summary: AI-Text-to-SQL, revolutionize database querying with AI-powered text-to-SQL.
Home-page: https://github.com/MinuraPunchihewa/ai-text-to-sql
License: GPL-3.0
Author: Minura Punchihewa
Author-email: minurapunchihewa17@gmail.com
Requires-Python: >=3.9
Classifier: License :: OSI Approved :: GNU General Public License v3 (GPLv3)
Classifier: Programming Language :: Python :: 3
Classifier: Programming Language :: Python :: 3.9
Classifier: Programming Language :: Python :: 3.10
Classifier: Programming Language :: Python :: 3.11
Classifier: Programming Language :: Python :: 3.12
Requires-Dist: openai (>=1.61.0,<2.0.0)
Requires-Dist: pandas (>=2.2.3,<3.0.0)
Requires-Dist: psycopg2-binary (>=2.9.10,<3.0.0)
Requires-Dist: pyodbc (>=5.2.0,<6.0.0)
Requires-Dist: pyyaml (>=6.0.2,<7.0.0)
Requires-Dist: sqlalchemy (>=2.0.37,<3.0.0)
Project-URL: PyPI, https://pypi.org/project/ai-text-to-sql/
Project-URL: Repository, https://github.com/MinuraPunchihewa/ai-text-to-sql
Project-URL: Release Notes, https://github.com/MinuraPunchihewa/releases
Project-URL: Source Code, https://github.com/MinuraPunchihewa/tree/main/ai_text_to_sql
